automapper/__init__.py
automapper/default_mapper.py
automapper/functions.py
automapper/mapper.py
automapper/mapping_plugin.py
automapper/sql_alchemy_mapper.py
automapper/types.py
advanced_automapper-0.1.15.dist-info/LICENSE
advanced_automapper-0.1.15.dist-info/METADATA
advanced_automapper-0.1.15.dist-info/WHEEL
advanced_automapper-0.1.15.dist-info/RECORD
