Metadata-Version: 2.1
Name: advanced-automapper
Version: 0.1.15
Summary: Object mapper based on type hints
Home-page: https://impalah.github.io/advanced-automapper/
License: MIT
Keywords: mapper,typehints,python
Author: impalah
Author-email: impalah@gmail.com
Requires-Python: >=3.10
Classifier: Development Status :: 4 - Beta
Classifier: Intended Audience :: Developers
Classifier: License :: OSI Approved :: MIT License
Classifier: Programming Language :: Python :: 3
Classifier: Programming Language :: Python :: 3.10
Classifier: Programming Language :: Python :: 3.11
Classifier: Programming Language :: Python :: 3.12
Classifier: Topic :: Software Development :: Libraries :: Python Modules
Requires-Dist: pydantic (>=2.7.1,<3.0.0)
Requires-Dist: sqlalchemy (>=2.0.30,<3.0.0)
Project-URL: Documentation, https://impalah.github.io/advanced-automapper/
Project-URL: Repository, https://github.com/impalah/advanced-automapper
Project-URL: Source, https://github.com/impalah/advanced-automapper
